setup.py
model_infer_utils/__init__.py
model_infer_utils/infer_task_mgr.py
model_infer_utils/model_config_mgr.py
model_infer_utils/param_parse_helper.py
model_infer_utils/redis_Infer_task_mgr.py
model_infer_utils/redis_warper.py
model_infer_utils/task_proto.py
model_infer_utils.egg-info/PKG-INFO
model_infer_utils.egg-info/SOURCES.txt
model_infer_utils.egg-info/dependency_links.txt
model_infer_utils.egg-info/requires.txt
model_infer_utils.egg-info/top_level.txt